tarta_api/__init__.py
tarta_api/job_search.py
tarta_api-1.0.0.dist-info/METADATA
tarta_api-1.0.0.dist-info/WHEEL
tarta_api-1.0.0.dist-info/top_level.txt
tarta_api-1.0.0.dist-info/RECORD
