Metadata-Version: 2.2
Name: tarta-api
Version: 1.0.0
Summary: Python wrapper for the Tarta API, designed to seamlessly integrate AI-powered job search functionality into your applications.
Home-page: https://tarta.ai/
Author: tarta.ai
Author-email: taras@tarta.ai
Project-URL: Homepage, https://tarta.ai/
Project-URL: Documentation, https://api.tarta.net/swagger/index.html
Project-URL: Source Code, https://github.com/tarta-ai/TartaAPI-python
Project-URL: Bug Tracker, https://github.com/tarta-ai/TartaAPI-python/issues
Classifier: Programming Language :: Python :: 3
Classifier: License :: OSI Approved :: MIT License
Classifier: Operating System :: OS Independent
Requires-Python: >=3.6
Requires-Dist: requests>=2.28.0
Dynamic: author
Dynamic: author-email
Dynamic: classifier
Dynamic: description
Dynamic: description-content-type
Dynamic: home-page
Dynamic: project-url
Dynamic: requires-dist
Dynamic: requires-python
Dynamic: summary
